{
  "user": "anyzicky",
  "repos": 1,
  "login": "anyzicky",
  "id": 2561762,
  "avatar_url": "https://avatars2.githubusercontent.com/u/2561762?v=3",
  "url": "https://api.github.com/users/anyzicky",
  "html_url": "https://github.com/anyzicky",
  "followers_url": "https://api.github.com/users/anyzicky/followers",
  "following_url": "https://api.github.com/users/anyzicky/following{/other_user}",
  "gists_url": "https://api.github.com/users/anyzicky/gists{/gist_id}",
  "starred_url": "https://api.github.com/users/anyzicky/starred{/owner}{/repo}",
  "subscriptions_url": "https://api.github.com/users/anyzicky/subscriptions",
  "organizations_url": "https://api.github.com/users/anyzicky/orgs",
  "repos_url": "https://api.github.com/users/anyzicky/repos",
  "events_url": "https://api.github.com/users/anyzicky/events{/privacy}",
  "received_events_url": "https://api.github.com/users/anyzicky/received_events",
  "type": "User",
  "site_admin": false,
  "name": null,
  "company": null,
  "blog": null,
  "location": null,
  "email": null,
  "hireable": null,
  "bio": null,
  "public_repos": 13,
  "public_gists": 1,
  "followers": 4,
  "following": 7,
  "created_at": "2012-10-15T06:30:25Z",
  "updated_at": "2017-02-27T16:51:17Z"
}