{
  "user": "Arosci",
  "repos": 1,
  "login": "Arosci",
  "id": 6702782,
  "avatar_url": "https://avatars0.githubusercontent.com/u/6702782?v=3",
  "url": "https://api.github.com/users/Arosci",
  "html_url": "https://github.com/Arosci",
  "followers_url": "https://api.github.com/users/Arosci/followers",
  "following_url": "https://api.github.com/users/Arosci/following{/other_user}",
  "gists_url": "https://api.github.com/users/Arosci/gists{/gist_id}",
  "starred_url": "https://api.github.com/users/Arosci/starred{/owner}{/repo}",
  "subscriptions_url": "https://api.github.com/users/Arosci/subscriptions",
  "organizations_url": "https://api.github.com/users/Arosci/orgs",
  "repos_url": "https://api.github.com/users/Arosci/repos",
  "events_url": "https://api.github.com/users/Arosci/events{/privacy}",
  "received_events_url": "https://api.github.com/users/Arosci/received_events",
  "type": "User",
  "site_admin": false,
  "name": null,
  "company": null,
  "blog": null,
  "location": "Italy",
  "email": "andrea.rosci@fwr.it",
  "hireable": null,
  "bio": null,
  "public_repos": 2,
  "public_gists": 0,
  "followers": 0,
  "following": 0,
  "created_at": "2014-02-17T08:36:16Z",
  "updated_at": "2017-01-06T22:17:18Z"
}