{
  "user": "Auo",
  "repos": 1,
  "login": "Auo",
  "id": 1984096,
  "avatar_url": "https://avatars0.githubusercontent.com/u/1984096?v=3",
  "url": "https://api.github.com/users/Auo",
  "html_url": "https://github.com/Auo",
  "followers_url": "https://api.github.com/users/Auo/followers",
  "following_url": "https://api.github.com/users/Auo/following{/other_user}",
  "gists_url": "https://api.github.com/users/Auo/gists{/gist_id}",
  "starred_url": "https://api.github.com/users/Auo/starred{/owner}{/repo}",
  "subscriptions_url": "https://api.github.com/users/Auo/subscriptions",
  "organizations_url": "https://api.github.com/users/Auo/orgs",
  "repos_url": "https://api.github.com/users/Auo/repos",
  "events_url": "https://api.github.com/users/Auo/events{/privacy}",
  "received_events_url": "https://api.github.com/users/Auo/received_events",
  "type": "User",
  "site_admin": false,
  "name": "Andreas Lindgren",
  "company": null,
  "blog": null,
  "location": null,
  "email": null,
  "hireable": null,
  "bio": null,
  "public_repos": 20,
  "public_gists": 0,
  "followers": 2,
  "following": 6,
  "created_at": "2012-07-16T12:29:00Z",
  "updated_at": "2017-02-12T12:58:57Z"
}