{
  "user": "bbbjr2013",
  "repos": 1,
  "login": "bbbjr2013",
  "id": 7232088,
  "avatar_url": "https://avatars2.githubusercontent.com/u/7232088?v=3",
  "url": "https://api.github.com/users/bbbjr2013",
  "html_url": "https://github.com/bbbjr2013",
  "followers_url": "https://api.github.com/users/bbbjr2013/followers",
  "following_url": "https://api.github.com/users/bbbjr2013/following{/other_user}",
  "gists_url": "https://api.github.com/users/bbbjr2013/gists{/gist_id}",
  "starred_url": "https://api.github.com/users/bbbjr2013/starred{/owner}{/repo}",
  "subscriptions_url": "https://api.github.com/users/bbbjr2013/subscriptions",
  "organizations_url": "https://api.github.com/users/bbbjr2013/orgs",
  "repos_url": "https://api.github.com/users/bbbjr2013/repos",
  "events_url": "https://api.github.com/users/bbbjr2013/events{/privacy}",
  "received_events_url": "https://api.github.com/users/bbbjr2013/received_events",
  "type": "User",
  "site_admin": false,
  "name": null,
  "company": null,
  "blog": null,
  "location": null,
  "email": null,
  "hireable": null,
  "bio": null,
  "public_repos": 9,
  "public_gists": 0,
  "followers": 1,
  "following": 2,
  "created_at": "2014-04-08T23:13:49Z",
  "updated_at": "2017-02-26T05:50:30Z"
}