{
  "user": "bluekezza",
  "repos": 1,
  "login": "bluekezza",
  "id": 4630483,
  "avatar_url": "https://avatars2.githubusercontent.com/u/4630483?v=3",
  "url": "https://api.github.com/users/bluekezza",
  "html_url": "https://github.com/bluekezza",
  "followers_url": "https://api.github.com/users/bluekezza/followers",
  "following_url": "https://api.github.com/users/bluekezza/following{/other_user}",
  "gists_url": "https://api.github.com/users/bluekezza/gists{/gist_id}",
  "starred_url": "https://api.github.com/users/bluekezza/starred{/owner}{/repo}",
  "subscriptions_url": "https://api.github.com/users/bluekezza/subscriptions",
  "organizations_url": "https://api.github.com/users/bluekezza/orgs",
  "repos_url": "https://api.github.com/users/bluekezza/repos",
  "events_url": "https://api.github.com/users/bluekezza/events{/privacy}",
  "received_events_url": "https://api.github.com/users/bluekezza/received_events",
  "type": "User",
  "site_admin": false,
  "name": "James Carey",
  "company": null,
  "blog": null,
  "location": null,
  "email": "james.anthony.carey@gmail.com",
  "hireable": null,
  "bio": null,
  "public_repos": 12,
  "public_gists": 0,
  "followers": 3,
  "following": 7,
  "created_at": "2013-06-06T12:33:34Z",
  "updated_at": "2017-02-16T09:23:47Z"
}