{
  "user": "clervens",
  "repos": 1,
  "login": "clervens",
  "id": 3706253,
  "avatar_url": "https://avatars1.githubusercontent.com/u/3706253?v=3",
  "url": "https://api.github.com/users/clervens",
  "html_url": "https://github.com/clervens",
  "followers_url": "https://api.github.com/users/clervens/followers",
  "following_url": "https://api.github.com/users/clervens/following{/other_user}",
  "gists_url": "https://api.github.com/users/clervens/gists{/gist_id}",
  "starred_url": "https://api.github.com/users/clervens/starred{/owner}{/repo}",
  "subscriptions_url": "https://api.github.com/users/clervens/subscriptions",
  "organizations_url": "https://api.github.com/users/clervens/orgs",
  "repos_url": "https://api.github.com/users/clervens/repos",
  "events_url": "https://api.github.com/users/clervens/events{/privacy}",
  "received_events_url": "https://api.github.com/users/clervens/received_events",
  "type": "User",
  "site_admin": false,
  "name": null,
  "company": null,
  "blog": null,
  "location": "Montréal, Québec, Canada",
  "email": null,
  "hireable": null,
  "bio": null,
  "public_repos": 18,
  "public_gists": 1,
  "followers": 1,
  "following": 0,
  "created_at": "2013-02-26T15:38:47Z",
  "updated_at": "2017-02-25T05:47:03Z"
}