{
  "user": "cmdcolin",
  "repos": 1,
  "login": "cmdcolin",
  "id": 6511937,
  "avatar_url": "https://avatars3.githubusercontent.com/u/6511937?v=3",
  "url": "https://api.github.com/users/cmdcolin",
  "html_url": "https://github.com/cmdcolin",
  "followers_url": "https://api.github.com/users/cmdcolin/followers",
  "following_url": "https://api.github.com/users/cmdcolin/following{/other_user}",
  "gists_url": "https://api.github.com/users/cmdcolin/gists{/gist_id}",
  "starred_url": "https://api.github.com/users/cmdcolin/starred{/owner}{/repo}",
  "subscriptions_url": "https://api.github.com/users/cmdcolin/subscriptions",
  "organizations_url": "https://api.github.com/users/cmdcolin/orgs",
  "repos_url": "https://api.github.com/users/cmdcolin/repos",
  "events_url": "https://api.github.com/users/cmdcolin/events{/privacy}",
  "received_events_url": "https://api.github.com/users/cmdcolin/received_events",
  "type": "User",
  "site_admin": false,
  "name": "Colin Diesh",
  "company": null,
  "blog": "http://cmdcolin.github.io",
  "location": "Michigan",
  "email": "colin.diesh@gmail.com",
  "hireable": true,
  "bio": null,
  "public_repos": 45,
  "public_gists": 37,
  "followers": 38,
  "following": 128,
  "created_at": "2014-01-27T07:17:54Z",
  "updated_at": "2017-02-24T14:38:11Z"
}