{
  "user": "codegateau",
  "repos": 1,
  "login": "codegateau",
  "id": 19389818,
  "avatar_url": "https://avatars2.githubusercontent.com/u/19389818?v=3",
  "url": "https://api.github.com/users/codegateau",
  "html_url": "https://github.com/codegateau",
  "followers_url": "https://api.github.com/users/codegateau/followers",
  "following_url": "https://api.github.com/users/codegateau/following{/other_user}",
  "gists_url": "https://api.github.com/users/codegateau/gists{/gist_id}",
  "starred_url": "https://api.github.com/users/codegateau/starred{/owner}{/repo}",
  "subscriptions_url": "https://api.github.com/users/codegateau/subscriptions",
  "organizations_url": "https://api.github.com/users/codegateau/orgs",
  "repos_url": "https://api.github.com/users/codegateau/repos",
  "events_url": "https://api.github.com/users/codegateau/events{/privacy}",
  "received_events_url": "https://api.github.com/users/codegateau/received_events",
  "type": "User",
  "site_admin": false,
  "name": "Billy Leo",
  "company": null,
  "blog": null,
  "location": null,
  "email": null,
  "hireable": null,
  "bio": null,
  "public_repos": 7,
  "public_gists": 0,
  "followers": 0,
  "following": 1,
  "created_at": "2016-05-16T13:38:06Z",
  "updated_at": "2017-02-04T16:28:24Z"
}