{
  "user": "cronvel",
  "repos": 2,
  "login": "cronvel",
  "id": 6891714,
  "avatar_url": "https://avatars1.githubusercontent.com/u/6891714?v=3",
  "url": "https://api.github.com/users/cronvel",
  "html_url": "https://github.com/cronvel",
  "followers_url": "https://api.github.com/users/cronvel/followers",
  "following_url": "https://api.github.com/users/cronvel/following{/other_user}",
  "gists_url": "https://api.github.com/users/cronvel/gists{/gist_id}",
  "starred_url": "https://api.github.com/users/cronvel/starred{/owner}{/repo}",
  "subscriptions_url": "https://api.github.com/users/cronvel/subscriptions",
  "organizations_url": "https://api.github.com/users/cronvel/orgs",
  "repos_url": "https://api.github.com/users/cronvel/repos",
  "events_url": "https://api.github.com/users/cronvel/events{/privacy}",
  "received_events_url": "https://api.github.com/users/cronvel/received_events",
  "type": "User",
  "site_admin": false,
  "name": "Cedric Ronvel",
  "company": "Freelance",
  "blog": "http://blog.soulserv.net",
  "location": "Paris / Aubenas (France)",
  "email": "cedric.ronvel@gmail.com",
  "hireable": null,
  "bio": null,
  "public_repos": 63,
  "public_gists": 0,
  "followers": 20,
  "following": 0,
  "created_at": "2014-03-08T13:48:51Z",
  "updated_at": "2015-11-25T11:10:34Z"
}