{
  "user": "CuiJie0212",
  "repos": 1,
  "login": "CuiJie0212",
  "id": 20900013,
  "avatar_url": "https://avatars3.githubusercontent.com/u/20900013?v=3",
  "url": "https://api.github.com/users/CuiJie0212",
  "html_url": "https://github.com/CuiJie0212",
  "followers_url": "https://api.github.com/users/CuiJie0212/followers",
  "following_url": "https://api.github.com/users/CuiJie0212/following{/other_user}",
  "gists_url": "https://api.github.com/users/CuiJie0212/gists{/gist_id}",
  "starred_url": "https://api.github.com/users/CuiJie0212/starred{/owner}{/repo}",
  "subscriptions_url": "https://api.github.com/users/CuiJie0212/subscriptions",
  "organizations_url": "https://api.github.com/users/CuiJie0212/orgs",
  "repos_url": "https://api.github.com/users/CuiJie0212/repos",
  "events_url": "https://api.github.com/users/CuiJie0212/events{/privacy}",
  "received_events_url": "https://api.github.com/users/CuiJie0212/received_events",
  "type": "User",
  "site_admin": false,
  "name": null,
  "company": null,
  "blog": null,
  "location": null,
  "email": null,
  "hireable": null,
  "bio": null,
  "public_repos": 0,
  "public_gists": 0,
  "followers": 0,
  "following": 0,
  "created_at": "2016-08-08T07:18:17Z",
  "updated_at": "2016-08-24T07:57:01Z"
}