{
  "user": "djaney",
  "repos": 1,
  "login": "djaney",
  "id": 2299010,
  "avatar_url": "https://avatars1.githubusercontent.com/u/2299010?v=3",
  "url": "https://api.github.com/users/djaney",
  "html_url": "https://github.com/djaney",
  "followers_url": "https://api.github.com/users/djaney/followers",
  "following_url": "https://api.github.com/users/djaney/following{/other_user}",
  "gists_url": "https://api.github.com/users/djaney/gists{/gist_id}",
  "starred_url": "https://api.github.com/users/djaney/starred{/owner}{/repo}",
  "subscriptions_url": "https://api.github.com/users/djaney/subscriptions",
  "organizations_url": "https://api.github.com/users/djaney/orgs",
  "repos_url": "https://api.github.com/users/djaney/repos",
  "events_url": "https://api.github.com/users/djaney/events{/privacy}",
  "received_events_url": "https://api.github.com/users/djaney/received_events",
  "type": "User",
  "site_admin": false,
  "name": "Djane Rey Mabelin",
  "company": "Arcanys, Inc.",
  "blog": "http://djaney.github.io/",
  "location": "Philippines",
  "email": "thedjaney@gmail.com",
  "hireable": null,
  "bio": "No time for github lately",
  "public_repos": 60,
  "public_gists": 22,
  "followers": 13,
  "following": 27,
  "created_at": "2012-09-07T11:51:19Z",
  "updated_at": "2017-02-04T20:25:10Z"
}