{
  "user": "dobiedad",
  "repos": 1,
  "login": "dobiedad",
  "id": 6469970,
  "avatar_url": "https://avatars3.githubusercontent.com/u/6469970?v=3",
  "url": "https://api.github.com/users/dobiedad",
  "html_url": "https://github.com/dobiedad",
  "followers_url": "https://api.github.com/users/dobiedad/followers",
  "following_url": "https://api.github.com/users/dobiedad/following{/other_user}",
  "gists_url": "https://api.github.com/users/dobiedad/gists{/gist_id}",
  "starred_url": "https://api.github.com/users/dobiedad/starred{/owner}{/repo}",
  "subscriptions_url": "https://api.github.com/users/dobiedad/subscriptions",
  "organizations_url": "https://api.github.com/users/dobiedad/orgs",
  "repos_url": "https://api.github.com/users/dobiedad/repos",
  "events_url": "https://api.github.com/users/dobiedad/events{/privacy}",
  "received_events_url": "https://api.github.com/users/dobiedad/received_events",
  "type": "User",
  "site_admin": false,
  "name": null,
  "company": "Featurist",
  "blog": "http://www.featurist.co.uk",
  "location": null,
  "email": "leo@featurist.co.uk",
  "hireable": null,
  "bio": null,
  "public_repos": 26,
  "public_gists": 0,
  "followers": 11,
  "following": 8,
  "created_at": "2014-01-22T09:56:45Z",
  "updated_at": "2017-02-24T12:37:26Z"
}