{
  "user": "ezekeal",
  "repos": 1,
  "login": "ezekeal",
  "id": 6458318,
  "avatar_url": "https://avatars2.githubusercontent.com/u/6458318?v=3",
  "url": "https://api.github.com/users/ezekeal",
  "html_url": "https://github.com/ezekeal",
  "followers_url": "https://api.github.com/users/ezekeal/followers",
  "following_url": "https://api.github.com/users/ezekeal/following{/other_user}",
  "gists_url": "https://api.github.com/users/ezekeal/gists{/gist_id}",
  "starred_url": "https://api.github.com/users/ezekeal/starred{/owner}{/repo}",
  "subscriptions_url": "https://api.github.com/users/ezekeal/subscriptions",
  "organizations_url": "https://api.github.com/users/ezekeal/orgs",
  "repos_url": "https://api.github.com/users/ezekeal/repos",
  "events_url": "https://api.github.com/users/ezekeal/events{/privacy}",
  "received_events_url": "https://api.github.com/users/ezekeal/received_events",
  "type": "User",
  "site_admin": false,
  "name": "Zach Koch",
  "company": null,
  "blog": null,
  "location": null,
  "email": null,
  "hireable": null,
  "bio": null,
  "public_repos": 45,
  "public_gists": 1,
  "followers": 9,
  "following": 48,
  "created_at": "2014-01-21T08:18:18Z",
  "updated_at": "2017-02-14T11:15:10Z"
}