{
  "user": "fritzvd",
  "repos": 1,
  "login": "fritzvd",
  "id": 160328,
  "avatar_url": "https://avatars3.githubusercontent.com/u/160328?v=3",
  "url": "https://api.github.com/users/fritzvd",
  "html_url": "https://github.com/fritzvd",
  "followers_url": "https://api.github.com/users/fritzvd/followers",
  "following_url": "https://api.github.com/users/fritzvd/following{/other_user}",
  "gists_url": "https://api.github.com/users/fritzvd/gists{/gist_id}",
  "starred_url": "https://api.github.com/users/fritzvd/starred{/owner}{/repo}",
  "subscriptions_url": "https://api.github.com/users/fritzvd/subscriptions",
  "organizations_url": "https://api.github.com/users/fritzvd/orgs",
  "repos_url": "https://api.github.com/users/fritzvd/repos",
  "events_url": "https://api.github.com/users/fritzvd/events{/privacy}",
  "received_events_url": "https://api.github.com/users/fritzvd/received_events",
  "type": "User",
  "site_admin": false,
  "name": "Fritz van Deventer",
  "company": null,
  "blog": "http://cheesesofmexico.com",
  "location": "Netherlands, South Africa",
  "email": "fritzvd+github@gmail.com",
  "hireable": null,
  "bio": "Makes music at cheesesofmexico.com codes for glory and fame for fun. teaches at han.nl. Gives talks about NES. Bakes bread.",
  "public_repos": 126,
  "public_gists": 21,
  "followers": 29,
  "following": 20,
  "created_at": "2009-12-01T12:58:22Z",
  "updated_at": "2017-02-22T18:52:19Z"
}