{
  "user": "hans-strudel",
  "repos": 1,
  "login": "hans-strudel",
  "id": 18598550,
  "avatar_url": "https://avatars3.githubusercontent.com/u/18598550?v=3",
  "url": "https://api.github.com/users/hans-strudel",
  "html_url": "https://github.com/hans-strudel",
  "followers_url": "https://api.github.com/users/hans-strudel/followers",
  "following_url": "https://api.github.com/users/hans-strudel/following{/other_user}",
  "gists_url": "https://api.github.com/users/hans-strudel/gists{/gist_id}",
  "starred_url": "https://api.github.com/users/hans-strudel/starred{/owner}{/repo}",
  "subscriptions_url": "https://api.github.com/users/hans-strudel/subscriptions",
  "organizations_url": "https://api.github.com/users/hans-strudel/orgs",
  "repos_url": "https://api.github.com/users/hans-strudel/repos",
  "events_url": "https://api.github.com/users/hans-strudel/events{/privacy}",
  "received_events_url": "https://api.github.com/users/hans-strudel/received_events",
  "type": "User",
  "site_admin": false,
  "name": null,
  "company": null,
  "blog": null,
  "location": "San Jose, CA",
  "email": null,
  "hireable": true,
  "bio": null,
  "public_repos": 20,
  "public_gists": 0,
  "followers": 0,
  "following": 0,
  "created_at": "2016-04-21T15:21:44Z",
  "updated_at": "2016-10-28T18:08:39Z"
}