{
  "user": "illeszsolt",
  "repos": 1,
  "login": "illeszsolt",
  "id": 17592275,
  "avatar_url": "https://avatars0.githubusercontent.com/u/17592275?v=3",
  "url": "https://api.github.com/users/illeszsolt",
  "html_url": "https://github.com/illeszsolt",
  "followers_url": "https://api.github.com/users/illeszsolt/followers",
  "following_url": "https://api.github.com/users/illeszsolt/following{/other_user}",
  "gists_url": "https://api.github.com/users/illeszsolt/gists{/gist_id}",
  "starred_url": "https://api.github.com/users/illeszsolt/starred{/owner}{/repo}",
  "subscriptions_url": "https://api.github.com/users/illeszsolt/subscriptions",
  "organizations_url": "https://api.github.com/users/illeszsolt/orgs",
  "repos_url": "https://api.github.com/users/illeszsolt/repos",
  "events_url": "https://api.github.com/users/illeszsolt/events{/privacy}",
  "received_events_url": "https://api.github.com/users/illeszsolt/received_events",
  "type": "User",
  "site_admin": false,
  "name": "Illés Zsolt",
  "company": "Slamby",
  "blog": null,
  "location": "Debrecen",
  "email": null,
  "hireable": null,
  "bio": null,
  "public_repos": 1,
  "public_gists": 0,
  "followers": 0,
  "following": 0,
  "created_at": "2016-03-02T11:41:05Z",
  "updated_at": "2016-12-15T18:38:48Z"
}