{
  "user": "jachinte",
  "repos": 1,
  "login": "jachinte",
  "id": 1284036,
  "avatar_url": "https://avatars1.githubusercontent.com/u/1284036?v=3",
  "url": "https://api.github.com/users/jachinte",
  "html_url": "https://github.com/jachinte",
  "followers_url": "https://api.github.com/users/jachinte/followers",
  "following_url": "https://api.github.com/users/jachinte/following{/other_user}",
  "gists_url": "https://api.github.com/users/jachinte/gists{/gist_id}",
  "starred_url": "https://api.github.com/users/jachinte/starred{/owner}{/repo}",
  "subscriptions_url": "https://api.github.com/users/jachinte/subscriptions",
  "organizations_url": "https://api.github.com/users/jachinte/orgs",
  "repos_url": "https://api.github.com/users/jachinte/repos",
  "events_url": "https://api.github.com/users/jachinte/events{/privacy}",
  "received_events_url": "https://api.github.com/users/jachinte/received_events",
  "type": "User",
  "site_admin": false,
  "name": "Miguel Jiménez",
  "company": null,
  "blog": "http://migueljimenez.co",
  "location": "Victoria, Canada",
  "email": null,
  "hireable": null,
  "bio": null,
  "public_repos": 24,
  "public_gists": 1,
  "followers": 18,
  "following": 19,
  "created_at": "2011-12-24T19:25:57Z",
  "updated_at": "2017-02-19T05:44:30Z"
}