{
  "user": "Jayin",
  "repos": 1,
  "login": "Jayin",
  "id": 2763894,
  "avatar_url": "https://avatars2.githubusercontent.com/u/2763894?v=3",
  "url": "https://api.github.com/users/Jayin",
  "html_url": "https://github.com/Jayin",
  "followers_url": "https://api.github.com/users/Jayin/followers",
  "following_url": "https://api.github.com/users/Jayin/following{/other_user}",
  "gists_url": "https://api.github.com/users/Jayin/gists{/gist_id}",
  "starred_url": "https://api.github.com/users/Jayin/starred{/owner}{/repo}",
  "subscriptions_url": "https://api.github.com/users/Jayin/subscriptions",
  "organizations_url": "https://api.github.com/users/Jayin/orgs",
  "repos_url": "https://api.github.com/users/Jayin/repos",
  "events_url": "https://api.github.com/users/Jayin/events{/privacy}",
  "received_events_url": "https://api.github.com/users/Jayin/received_events",
  "type": "User",
  "site_admin": false,
  "name": "Jayin Ton",
  "company": "@Zhutibang @ztbcms ",
  "blog": "http://jayinton.com",
  "location": " Guangzhou, China",
  "email": "tonjayin@gmail.com",
  "hireable": null,
  "bio": "creator of @EManual,maintainer of @ztbcms ",
  "public_repos": 144,
  "public_gists": 31,
  "followers": 153,
  "following": 151,
  "created_at": "2012-11-10T04:32:48Z",
  "updated_at": "2017-02-15T09:02:45Z"
}