{
  "user": "jiahaog",
  "repos": 1,
  "login": "jiahaog",
  "id": 7111741,
  "avatar_url": "https://avatars0.githubusercontent.com/u/7111741?v=3",
  "url": "https://api.github.com/users/jiahaog",
  "html_url": "https://github.com/jiahaog",
  "followers_url": "https://api.github.com/users/jiahaog/followers",
  "following_url": "https://api.github.com/users/jiahaog/following{/other_user}",
  "gists_url": "https://api.github.com/users/jiahaog/gists{/gist_id}",
  "starred_url": "https://api.github.com/users/jiahaog/starred{/owner}{/repo}",
  "subscriptions_url": "https://api.github.com/users/jiahaog/subscriptions",
  "organizations_url": "https://api.github.com/users/jiahaog/orgs",
  "repos_url": "https://api.github.com/users/jiahaog/repos",
  "events_url": "https://api.github.com/users/jiahaog/events{/privacy}",
  "received_events_url": "https://api.github.com/users/jiahaog/received_events",
  "type": "User",
  "site_admin": false,
  "name": "Jia Hao",
  "company": "Grab",
  "blog": "https://jiahaog.com",
  "location": "Singapore",
  "email": "jiahaog@gmail.com",
  "hireable": true,
  "bio": "@jiahaog",
  "public_repos": 38,
  "public_gists": 9,
  "followers": 241,
  "following": 16,
  "created_at": "2014-03-31T04:10:58Z",
  "updated_at": "2017-02-17T11:44:20Z"
}