{
  "user": "JimLiu",
  "repos": 1,
  "login": "JimLiu",
  "id": 648674,
  "avatar_url": "https://avatars0.githubusercontent.com/u/648674?v=3",
  "url": "https://api.github.com/users/JimLiu",
  "html_url": "https://github.com/JimLiu",
  "followers_url": "https://api.github.com/users/JimLiu/followers",
  "following_url": "https://api.github.com/users/JimLiu/following{/other_user}",
  "gists_url": "https://api.github.com/users/JimLiu/gists{/gist_id}",
  "starred_url": "https://api.github.com/users/JimLiu/starred{/owner}{/repo}",
  "subscriptions_url": "https://api.github.com/users/JimLiu/subscriptions",
  "organizations_url": "https://api.github.com/users/JimLiu/orgs",
  "repos_url": "https://api.github.com/users/JimLiu/repos",
  "events_url": "https://api.github.com/users/JimLiu/events{/privacy}",
  "received_events_url": "https://api.github.com/users/JimLiu/received_events",
  "type": "User",
  "site_admin": false,
  "name": "Jim Liu",
  "company": null,
  "blog": null,
  "location": "Chicago, IL",
  "email": "junminliu@gmail.com",
  "hireable": true,
  "bio": null,
  "public_repos": 56,
  "public_gists": 8,
  "followers": 351,
  "following": 88,
  "created_at": "2011-03-03T09:18:48Z",
  "updated_at": "2017-02-16T16:05:39Z"
}