{
  "user": "joengelm",
  "repos": 1,
  "login": "joengelm",
  "id": 5783424,
  "avatar_url": "https://avatars0.githubusercontent.com/u/5783424?v=3",
  "url": "https://api.github.com/users/joengelm",
  "html_url": "https://github.com/joengelm",
  "followers_url": "https://api.github.com/users/joengelm/followers",
  "following_url": "https://api.github.com/users/joengelm/following{/other_user}",
  "gists_url": "https://api.github.com/users/joengelm/gists{/gist_id}",
  "starred_url": "https://api.github.com/users/joengelm/starred{/owner}{/repo}",
  "subscriptions_url": "https://api.github.com/users/joengelm/subscriptions",
  "organizations_url": "https://api.github.com/users/joengelm/orgs",
  "repos_url": "https://api.github.com/users/joengelm/repos",
  "events_url": "https://api.github.com/users/joengelm/events{/privacy}",
  "received_events_url": "https://api.github.com/users/joengelm/received_events",
  "type": "User",
  "site_admin": false,
  "name": "Joe Engelman",
  "company": null,
  "blog": "joengelm.github.io",
  "location": "Providence, RI",
  "email": "engelman.joe@gmail.com",
  "hireable": true,
  "bio": null,
  "public_repos": 14,
  "public_gists": 0,
  "followers": 10,
  "following": 11,
  "created_at": "2013-10-26T20:19:39Z",
  "updated_at": "2017-02-23T05:53:02Z"
}