{
  "user": "Kilian",
  "repos": 4,
  "login": "Kilian",
  "id": 41970,
  "avatar_url": "https://avatars0.githubusercontent.com/u/41970?v=3",
  "url": "https://api.github.com/users/Kilian",
  "html_url": "https://github.com/Kilian",
  "followers_url": "https://api.github.com/users/Kilian/followers",
  "following_url": "https://api.github.com/users/Kilian/following{/other_user}",
  "gists_url": "https://api.github.com/users/Kilian/gists{/gist_id}",
  "starred_url": "https://api.github.com/users/Kilian/starred{/owner}{/repo}",
  "subscriptions_url": "https://api.github.com/users/Kilian/subscriptions",
  "organizations_url": "https://api.github.com/users/Kilian/orgs",
  "repos_url": "https://api.github.com/users/Kilian/repos",
  "events_url": "https://api.github.com/users/Kilian/events{/privacy}",
  "received_events_url": "https://api.github.com/users/Kilian/received_events",
  "type": "User",
  "site_admin": false,
  "name": "Kilian Valkhof",
  "company": "Fluxility",
  "blog": "http://kilianvalkhof.com",
  "location": "Zoetermeer, the netherlands",
  "email": "kilian@kilianvalkhof.com",
  "hireable": null,
  "bio": null,
  "public_repos": 39,
  "public_gists": 7,
  "followers": 168,
  "following": 56,
  "created_at": "2008-12-21T18:42:52Z",
  "updated_at": "2017-02-18T15:14:37Z"
}