{
  "user": "lifetilt88",
  "repos": 1,
  "login": "lifetilt88",
  "id": 16262347,
  "avatar_url": "https://avatars2.githubusercontent.com/u/16262347?v=3",
  "url": "https://api.github.com/users/lifetilt88",
  "html_url": "https://github.com/lifetilt88",
  "followers_url": "https://api.github.com/users/lifetilt88/followers",
  "following_url": "https://api.github.com/users/lifetilt88/following{/other_user}",
  "gists_url": "https://api.github.com/users/lifetilt88/gists{/gist_id}",
  "starred_url": "https://api.github.com/users/lifetilt88/starred{/owner}{/repo}",
  "subscriptions_url": "https://api.github.com/users/lifetilt88/subscriptions",
  "organizations_url": "https://api.github.com/users/lifetilt88/orgs",
  "repos_url": "https://api.github.com/users/lifetilt88/repos",
  "events_url": "https://api.github.com/users/lifetilt88/events{/privacy}",
  "received_events_url": "https://api.github.com/users/lifetilt88/received_events",
  "type": "User",
  "site_admin": false,
  "name": "Gunnar M Norred",
  "company": null,
  "blog": null,
  "location": null,
  "email": null,
  "hireable": true,
  "bio": "DePauw 37 - Wabash 34",
  "public_repos": 3,
  "public_gists": 0,
  "followers": 0,
  "following": 0,
  "created_at": "2015-12-12T00:45:06Z",
  "updated_at": "2017-02-21T16:55:12Z"
}