{
  "user": "listen1",
  "repos": 1,
  "login": "listen1",
  "id": 18599108,
  "avatar_url": "https://avatars0.githubusercontent.com/u/18599108?v=3",
  "url": "https://api.github.com/users/listen1",
  "html_url": "https://github.com/listen1",
  "followers_url": "https://api.github.com/users/listen1/followers",
  "following_url": "https://api.github.com/users/listen1/following{/other_user}",
  "gists_url": "https://api.github.com/users/listen1/gists{/gist_id}",
  "starred_url": "https://api.github.com/users/listen1/starred{/owner}{/repo}",
  "subscriptions_url": "https://api.github.com/users/listen1/subscriptions",
  "organizations_url": "https://api.github.com/users/listen1/orgs",
  "repos_url": "https://api.github.com/users/listen1/repos",
  "events_url": "https://api.github.com/users/listen1/events{/privacy}",
  "received_events_url": "https://api.github.com/users/listen1/received_events",
  "type": "User",
  "site_admin": false,
  "name": "Listen 1",
  "company": null,
  "blog": "https://twitter.com/githublisten1",
  "location": null,
  "email": "githublisten1@gmail.com",
  "hireable": null,
  "bio": "one for all free music in China",
  "public_repos": 4,
  "public_gists": 0,
  "followers": 240,
  "following": 0,
  "created_at": "2016-04-21T15:53:54Z",
  "updated_at": "2016-07-20T06:30:32Z"
}