{
  "user": "loics2",
  "repos": 1,
  "login": "loics2",
  "id": 1841684,
  "avatar_url": "https://avatars1.githubusercontent.com/u/1841684?v=3",
  "url": "https://api.github.com/users/loics2",
  "html_url": "https://github.com/loics2",
  "followers_url": "https://api.github.com/users/loics2/followers",
  "following_url": "https://api.github.com/users/loics2/following{/other_user}",
  "gists_url": "https://api.github.com/users/loics2/gists{/gist_id}",
  "starred_url": "https://api.github.com/users/loics2/starred{/owner}{/repo}",
  "subscriptions_url": "https://api.github.com/users/loics2/subscriptions",
  "organizations_url": "https://api.github.com/users/loics2/orgs",
  "repos_url": "https://api.github.com/users/loics2/repos",
  "events_url": "https://api.github.com/users/loics2/events{/privacy}",
  "received_events_url": "https://api.github.com/users/loics2/received_events",
  "type": "User",
  "site_admin": false,
  "name": "Loïc Stankovic",
  "company": null,
  "blog": null,
  "location": "Switzerland",
  "email": "loicstankovic@hotmail.com",
  "hireable": null,
  "bio": "CS student at HEIA-FR",
  "public_repos": 4,
  "public_gists": 0,
  "followers": 5,
  "following": 0,
  "created_at": "2012-06-12T08:53:19Z",
  "updated_at": "2017-02-18T05:45:15Z"
}