{
  "user": "MarceloAlves",
  "repos": 1,
  "login": "MarceloAlves",
  "id": 216782,
  "avatar_url": "https://avatars2.githubusercontent.com/u/216782?v=3",
  "url": "https://api.github.com/users/MarceloAlves",
  "html_url": "https://github.com/MarceloAlves",
  "followers_url": "https://api.github.com/users/MarceloAlves/followers",
  "following_url": "https://api.github.com/users/MarceloAlves/following{/other_user}",
  "gists_url": "https://api.github.com/users/MarceloAlves/gists{/gist_id}",
  "starred_url": "https://api.github.com/users/MarceloAlves/starred{/owner}{/repo}",
  "subscriptions_url": "https://api.github.com/users/MarceloAlves/subscriptions",
  "organizations_url": "https://api.github.com/users/MarceloAlves/orgs",
  "repos_url": "https://api.github.com/users/MarceloAlves/repos",
  "events_url": "https://api.github.com/users/MarceloAlves/events{/privacy}",
  "received_events_url": "https://api.github.com/users/MarceloAlves/received_events",
  "type": "User",
  "site_admin": false,
  "name": "Marcelo Alves",
  "company": "Valley Agricultural Software",
  "blog": "http://www.marceloalves.com",
  "location": "Tulare, CA",
  "email": null,
  "hireable": null,
  "bio": "Ruby Developer at Valley Agricultural Software",
  "public_repos": 27,
  "public_gists": 6,
  "followers": 17,
  "following": 16,
  "created_at": "2010-03-05T19:10:15Z",
  "updated_at": "2017-02-28T20:38:28Z"
}