{
  "user": "maxkueng",
  "repos": 2,
  "login": "maxkueng",
  "id": 168709,
  "avatar_url": "https://avatars2.githubusercontent.com/u/168709?v=3",
  "url": "https://api.github.com/users/maxkueng",
  "html_url": "https://github.com/maxkueng",
  "followers_url": "https://api.github.com/users/maxkueng/followers",
  "following_url": "https://api.github.com/users/maxkueng/following{/other_user}",
  "gists_url": "https://api.github.com/users/maxkueng/gists{/gist_id}",
  "starred_url": "https://api.github.com/users/maxkueng/starred{/owner}{/repo}",
  "subscriptions_url": "https://api.github.com/users/maxkueng/subscriptions",
  "organizations_url": "https://api.github.com/users/maxkueng/orgs",
  "repos_url": "https://api.github.com/users/maxkueng/repos",
  "events_url": "https://api.github.com/users/maxkueng/events{/privacy}",
  "received_events_url": "https://api.github.com/users/maxkueng/received_events",
  "type": "User",
  "site_admin": false,
  "name": "Max Kueng",
  "company": "@smallpdf",
  "blog": "http://maxkueng.com/contact",
  "location": "Zurich, Switzerland",
  "email": null,
  "hireable": null,
  "bio": null,
  "public_repos": 67,
  "public_gists": 18,
  "followers": 66,
  "following": 20,
  "created_at": "2009-12-17T00:41:39Z",
  "updated_at": "2017-02-27T11:37:17Z"
}