{
  "user": "meowtec",
  "repos": 3,
  "login": "meowtec",
  "id": 4006436,
  "avatar_url": "https://avatars0.githubusercontent.com/u/4006436?v=3",
  "url": "https://api.github.com/users/meowtec",
  "html_url": "https://github.com/meowtec",
  "followers_url": "https://api.github.com/users/meowtec/followers",
  "following_url": "https://api.github.com/users/meowtec/following{/other_user}",
  "gists_url": "https://api.github.com/users/meowtec/gists{/gist_id}",
  "starred_url": "https://api.github.com/users/meowtec/starred{/owner}{/repo}",
  "subscriptions_url": "https://api.github.com/users/meowtec/subscriptions",
  "organizations_url": "https://api.github.com/users/meowtec/orgs",
  "repos_url": "https://api.github.com/users/meowtec/repos",
  "events_url": "https://api.github.com/users/meowtec/events{/privacy}",
  "received_events_url": "https://api.github.com/users/meowtec/received_events",
  "type": "User",
  "site_admin": false,
  "name": "Berton Zhu",
  "company": "Alipay",
  "blog": "https://meowtec.github.io/",
  "location": "Alaska",
  "email": "bertonzh@gmail.com",
  "hireable": null,
  "bio": null,
  "public_repos": 36,
  "public_gists": 2,
  "followers": 54,
  "following": 4,
  "created_at": "2013-03-29T15:17:31Z",
  "updated_at": "2016-11-11T03:39:36Z"
}