{
  "user": "microbuilder",
  "repos": 1,
  "login": "microbuilder",
  "id": 181073,
  "avatar_url": "https://avatars0.githubusercontent.com/u/181073?v=3",
  "url": "https://api.github.com/users/microbuilder",
  "html_url": "https://github.com/microbuilder",
  "followers_url": "https://api.github.com/users/microbuilder/followers",
  "following_url": "https://api.github.com/users/microbuilder/following{/other_user}",
  "gists_url": "https://api.github.com/users/microbuilder/gists{/gist_id}",
  "starred_url": "https://api.github.com/users/microbuilder/starred{/owner}{/repo}",
  "subscriptions_url": "https://api.github.com/users/microbuilder/subscriptions",
  "organizations_url": "https://api.github.com/users/microbuilder/orgs",
  "repos_url": "https://api.github.com/users/microbuilder/repos",
  "events_url": "https://api.github.com/users/microbuilder/events{/privacy}",
  "received_events_url": "https://api.github.com/users/microbuilder/received_events",
  "type": "User",
  "site_admin": false,
  "name": "Kevin Townsend",
  "company": "microBuilder.io",
  "blog": "http://www.microbuilder.io",
  "location": "Paris, France",
  "email": null,
  "hireable": null,
  "bio": null,
  "public_repos": 14,
  "public_gists": 1,
  "followers": 167,
  "following": 6,
  "created_at": "2010-01-13T00:04:22Z",
  "updated_at": "2017-02-16T12:49:24Z"
}