{
  "user": "minodisk",
  "repos": 1,
  "login": "minodisk",
  "id": 514164,
  "avatar_url": "https://avatars0.githubusercontent.com/u/514164?v=3",
  "url": "https://api.github.com/users/minodisk",
  "html_url": "https://github.com/minodisk",
  "followers_url": "https://api.github.com/users/minodisk/followers",
  "following_url": "https://api.github.com/users/minodisk/following{/other_user}",
  "gists_url": "https://api.github.com/users/minodisk/gists{/gist_id}",
  "starred_url": "https://api.github.com/users/minodisk/starred{/owner}{/repo}",
  "subscriptions_url": "https://api.github.com/users/minodisk/subscriptions",
  "organizations_url": "https://api.github.com/users/minodisk/orgs",
  "repos_url": "https://api.github.com/users/minodisk/repos",
  "events_url": "https://api.github.com/users/minodisk/events{/privacy}",
  "received_events_url": "https://api.github.com/users/minodisk/received_events",
  "type": "User",
  "site_admin": false,
  "name": "Daisuke Mino",
  "company": "Syoya, Inc",
  "blog": null,
  "location": "Tokyo, Japan",
  "email": null,
  "hireable": null,
  "bio": null,
  "public_repos": 142,
  "public_gists": 44,
  "followers": 30,
  "following": 34,
  "created_at": "2010-12-08T04:49:25Z",
  "updated_at": "2017-02-28T09:11:13Z"
}