{
  "user": "miwehrs",
  "repos": 1,
  "login": "miwehrs",
  "id": 10684265,
  "avatar_url": "https://avatars1.githubusercontent.com/u/10684265?v=3",
  "url": "https://api.github.com/users/miwehrs",
  "html_url": "https://github.com/miwehrs",
  "followers_url": "https://api.github.com/users/miwehrs/followers",
  "following_url": "https://api.github.com/users/miwehrs/following{/other_user}",
  "gists_url": "https://api.github.com/users/miwehrs/gists{/gist_id}",
  "starred_url": "https://api.github.com/users/miwehrs/starred{/owner}{/repo}",
  "subscriptions_url": "https://api.github.com/users/miwehrs/subscriptions",
  "organizations_url": "https://api.github.com/users/miwehrs/orgs",
  "repos_url": "https://api.github.com/users/miwehrs/repos",
  "events_url": "https://api.github.com/users/miwehrs/events{/privacy}",
  "received_events_url": "https://api.github.com/users/miwehrs/received_events",
  "type": "User",
  "site_admin": false,
  "name": null,
  "company": null,
  "blog": null,
  "location": null,
  "email": null,
  "hireable": null,
  "bio": null,
  "public_repos": 1,
  "public_gists": 0,
  "followers": 0,
  "following": 0,
  "created_at": "2015-01-24T13:13:17Z",
  "updated_at": "2017-02-20T16:08:55Z"
}