{
  "user": "nkoriath",
  "repos": 1,
  "login": "nkoriath",
  "id": 6013877,
  "avatar_url": "https://avatars0.githubusercontent.com/u/6013877?v=3",
  "url": "https://api.github.com/users/nkoriath",
  "html_url": "https://github.com/nkoriath",
  "followers_url": "https://api.github.com/users/nkoriath/followers",
  "following_url": "https://api.github.com/users/nkoriath/following{/other_user}",
  "gists_url": "https://api.github.com/users/nkoriath/gists{/gist_id}",
  "starred_url": "https://api.github.com/users/nkoriath/starred{/owner}{/repo}",
  "subscriptions_url": "https://api.github.com/users/nkoriath/subscriptions",
  "organizations_url": "https://api.github.com/users/nkoriath/orgs",
  "repos_url": "https://api.github.com/users/nkoriath/repos",
  "events_url": "https://api.github.com/users/nkoriath/events{/privacy}",
  "received_events_url": "https://api.github.com/users/nkoriath/received_events",
  "type": "User",
  "site_admin": false,
  "name": null,
  "company": "@motive-io ",
  "blog": "nolankoriath.com",
  "location": "Vancouver BC",
  "email": null,
  "hireable": null,
  "bio": "Software Engineer at Motive.io",
  "public_repos": 2,
  "public_gists": 0,
  "followers": 12,
  "following": 5,
  "created_at": "2013-11-22T21:33:57Z",
  "updated_at": "2017-02-09T19:17:13Z"
}