{
  "user": "noffle",
  "repos": 4,
  "login": "noffle",
  "id": 489362,
  "avatar_url": "https://avatars1.githubusercontent.com/u/489362?v=3",
  "url": "https://api.github.com/users/noffle",
  "html_url": "https://github.com/noffle",
  "followers_url": "https://api.github.com/users/noffle/followers",
  "following_url": "https://api.github.com/users/noffle/following{/other_user}",
  "gists_url": "https://api.github.com/users/noffle/gists{/gist_id}",
  "starred_url": "https://api.github.com/users/noffle/starred{/owner}{/repo}",
  "subscriptions_url": "https://api.github.com/users/noffle/subscriptions",
  "organizations_url": "https://api.github.com/users/noffle/orgs",
  "repos_url": "https://api.github.com/users/noffle/repos",
  "events_url": "https://api.github.com/users/noffle/events{/privacy}",
  "received_events_url": "https://api.github.com/users/noffle/received_events",
  "type": "User",
  "site_admin": false,
  "name": "Stephen Whitmore",
  "company": null,
  "blog": "http://blog.eight45.net",
  "location": "San Jose",
  "email": null,
  "hireable": null,
  "bio": "Grow the commons with P2P tools that empower individuals & communities!",
  "public_repos": 235,
  "public_gists": 8,
  "followers": 205,
  "following": 69,
  "created_at": "2010-11-20T04:34:02Z",
  "updated_at": "2017-02-25T00:31:29Z"
}