{
  "user": "nrabinowitz",
  "repos": 1,
  "login": "nrabinowitz",
  "id": 163940,
  "avatar_url": "https://avatars2.githubusercontent.com/u/163940?v=3",
  "url": "https://api.github.com/users/nrabinowitz",
  "html_url": "https://github.com/nrabinowitz",
  "followers_url": "https://api.github.com/users/nrabinowitz/followers",
  "following_url": "https://api.github.com/users/nrabinowitz/following{/other_user}",
  "gists_url": "https://api.github.com/users/nrabinowitz/gists{/gist_id}",
  "starred_url": "https://api.github.com/users/nrabinowitz/starred{/owner}{/repo}",
  "subscriptions_url": "https://api.github.com/users/nrabinowitz/subscriptions",
  "organizations_url": "https://api.github.com/users/nrabinowitz/orgs",
  "repos_url": "https://api.github.com/users/nrabinowitz/repos",
  "events_url": "https://api.github.com/users/nrabinowitz/events{/privacy}",
  "received_events_url": "https://api.github.com/users/nrabinowitz/received_events",
  "type": "User",
  "site_admin": false,
  "name": "Nick Rabinowitz",
  "company": null,
  "blog": "www.nickrabinowitz.com",
  "location": "Oakland, CA",
  "email": null,
  "hireable": null,
  "bio": null,
  "public_repos": 19,
  "public_gists": 10,
  "followers": 78,
  "following": 3,
  "created_at": "2009-12-07T19:56:59Z",
  "updated_at": "2017-01-13T22:56:23Z"
}