{
  "user": "obvio171",
  "repos": 1,
  "login": "obvio171",
  "id": 4315,
  "avatar_url": "https://avatars0.githubusercontent.com/u/4315?v=3",
  "url": "https://api.github.com/users/obvio171",
  "html_url": "https://github.com/obvio171",
  "followers_url": "https://api.github.com/users/obvio171/followers",
  "following_url": "https://api.github.com/users/obvio171/following{/other_user}",
  "gists_url": "https://api.github.com/users/obvio171/gists{/gist_id}",
  "starred_url": "https://api.github.com/users/obvio171/starred{/owner}{/repo}",
  "subscriptions_url": "https://api.github.com/users/obvio171/subscriptions",
  "organizations_url": "https://api.github.com/users/obvio171/orgs",
  "repos_url": "https://api.github.com/users/obvio171/repos",
  "events_url": "https://api.github.com/users/obvio171/events{/privacy}",
  "received_events_url": "https://api.github.com/users/obvio171/received_events",
  "type": "User",
  "site_admin": false,
  "name": "Helder Ribeiro",
  "company": "Rádio 2an",
  "blog": "https://twitter.com/2anlive",
  "location": "Campinas, Brazil",
  "email": null,
  "hireable": null,
  "bio": null,
  "public_repos": 63,
  "public_gists": 29,
  "followers": 58,
  "following": 18,
  "created_at": "2008-04-02T19:15:44Z",
  "updated_at": "2017-02-16T20:04:44Z"
}