{
  "user": "phillipalexander",
  "repos": 1,
  "login": "phillipalexander",
  "id": 1577682,
  "avatar_url": "https://avatars3.githubusercontent.com/u/1577682?v=3",
  "url": "https://api.github.com/users/phillipalexander",
  "html_url": "https://github.com/phillipalexander",
  "followers_url": "https://api.github.com/users/phillipalexander/followers",
  "following_url": "https://api.github.com/users/phillipalexander/following{/other_user}",
  "gists_url": "https://api.github.com/users/phillipalexander/gists{/gist_id}",
  "starred_url": "https://api.github.com/users/phillipalexander/starred{/owner}{/repo}",
  "subscriptions_url": "https://api.github.com/users/phillipalexander/subscriptions",
  "organizations_url": "https://api.github.com/users/phillipalexander/orgs",
  "repos_url": "https://api.github.com/users/phillipalexander/repos",
  "events_url": "https://api.github.com/users/phillipalexander/events{/privacy}",
  "received_events_url": "https://api.github.com/users/phillipalexander/received_events",
  "type": "User",
  "site_admin": false,
  "name": "Phillip Alexander",
  "company": "@hackreactor",
  "blog": "http://phillipalexander.io",
  "location": "San Francisco",
  "email": "git@phillipalexander.io",
  "hireable": null,
  "bio": "Chief Product Officer at Hack Reactor",
  "public_repos": 58,
  "public_gists": 24,
  "followers": 277,
  "following": 50,
  "created_at": "2012-03-26T20:39:00Z",
  "updated_at": "2017-02-18T20:07:13Z"
}