{
  "user": "raphaelokon",
  "repos": 1,
  "login": "raphaelokon",
  "id": 527631,
  "avatar_url": "https://avatars3.githubusercontent.com/u/527631?v=3",
  "url": "https://api.github.com/users/raphaelokon",
  "html_url": "https://github.com/raphaelokon",
  "followers_url": "https://api.github.com/users/raphaelokon/followers",
  "following_url": "https://api.github.com/users/raphaelokon/following{/other_user}",
  "gists_url": "https://api.github.com/users/raphaelokon/gists{/gist_id}",
  "starred_url": "https://api.github.com/users/raphaelokon/starred{/owner}{/repo}",
  "subscriptions_url": "https://api.github.com/users/raphaelokon/subscriptions",
  "organizations_url": "https://api.github.com/users/raphaelokon/orgs",
  "repos_url": "https://api.github.com/users/raphaelokon/repos",
  "events_url": "https://api.github.com/users/raphaelokon/events{/privacy}",
  "received_events_url": "https://api.github.com/users/raphaelokon/received_events",
  "type": "User",
  "site_admin": false,
  "name": "Raphael Okon",
  "company": null,
  "blog": null,
  "location": "~",
  "email": null,
  "hireable": null,
  "bio": null,
  "public_repos": 10,
  "public_gists": 0,
  "followers": 13,
  "following": 7,
  "created_at": "2010-12-17T18:46:40Z",
  "updated_at": "2017-02-28T19:54:42Z"
}