{
  "user": "sameer-chauhan",
  "repos": 1,
  "login": "sameer-chauhan",
  "id": 22088646,
  "avatar_url": "https://avatars0.githubusercontent.com/u/22088646?v=3",
  "url": "https://api.github.com/users/sameer-chauhan",
  "html_url": "https://github.com/sameer-chauhan",
  "followers_url": "https://api.github.com/users/sameer-chauhan/followers",
  "following_url": "https://api.github.com/users/sameer-chauhan/following{/other_user}",
  "gists_url": "https://api.github.com/users/sameer-chauhan/gists{/gist_id}",
  "starred_url": "https://api.github.com/users/sameer-chauhan/starred{/owner}{/repo}",
  "subscriptions_url": "https://api.github.com/users/sameer-chauhan/subscriptions",
  "organizations_url": "https://api.github.com/users/sameer-chauhan/orgs",
  "repos_url": "https://api.github.com/users/sameer-chauhan/repos",
  "events_url": "https://api.github.com/users/sameer-chauhan/events{/privacy}",
  "received_events_url": "https://api.github.com/users/sameer-chauhan/received_events",
  "type": "User",
  "site_admin": false,
  "name": null,
  "company": null,
  "blog": null,
  "location": null,
  "email": null,
  "hireable": null,
  "bio": null,
  "public_repos": 0,
  "public_gists": 0,
  "followers": 0,
  "following": 0,
  "created_at": "2016-09-09T01:17:17Z",
  "updated_at": "2017-01-25T08:53:49Z"
}