{
  "user": "thefakegm",
  "repos": 1,
  "login": "thefakegm",
  "id": 19489411,
  "avatar_url": "https://avatars2.githubusercontent.com/u/19489411?v=3",
  "url": "https://api.github.com/users/thefakegm",
  "html_url": "https://github.com/thefakegm",
  "followers_url": "https://api.github.com/users/thefakegm/followers",
  "following_url": "https://api.github.com/users/thefakegm/following{/other_user}",
  "gists_url": "https://api.github.com/users/thefakegm/gists{/gist_id}",
  "starred_url": "https://api.github.com/users/thefakegm/starred{/owner}{/repo}",
  "subscriptions_url": "https://api.github.com/users/thefakegm/subscriptions",
  "organizations_url": "https://api.github.com/users/thefakegm/orgs",
  "repos_url": "https://api.github.com/users/thefakegm/repos",
  "events_url": "https://api.github.com/users/thefakegm/events{/privacy}",
  "received_events_url": "https://api.github.com/users/thefakegm/received_events",
  "type": "User",
  "site_admin": false,
  "name": null,
  "company": null,
  "blog": null,
  "location": null,
  "email": null,
  "hireable": null,
  "bio": null,
  "public_repos": 12,
  "public_gists": 0,
  "followers": 0,
  "following": 0,
  "created_at": "2016-05-20T11:08:54Z",
  "updated_at": "2017-02-25T09:04:14Z"
}