{
  "user": "trioletas",
  "repos": 1,
  "login": "trioletas",
  "id": 4508414,
  "avatar_url": "https://avatars1.githubusercontent.com/u/4508414?v=3",
  "url": "https://api.github.com/users/trioletas",
  "html_url": "https://github.com/trioletas",
  "followers_url": "https://api.github.com/users/trioletas/followers",
  "following_url": "https://api.github.com/users/trioletas/following{/other_user}",
  "gists_url": "https://api.github.com/users/trioletas/gists{/gist_id}",
  "starred_url": "https://api.github.com/users/trioletas/starred{/owner}{/repo}",
  "subscriptions_url": "https://api.github.com/users/trioletas/subscriptions",
  "organizations_url": "https://api.github.com/users/trioletas/orgs",
  "repos_url": "https://api.github.com/users/trioletas/repos",
  "events_url": "https://api.github.com/users/trioletas/events{/privacy}",
  "received_events_url": "https://api.github.com/users/trioletas/received_events",
  "type": "User",
  "site_admin": false,
  "name": null,
  "company": null,
  "blog": null,
  "location": null,
  "email": null,
  "hireable": null,
  "bio": null,
  "public_repos": 3,
  "public_gists": 0,
  "followers": 6,
  "following": 24,
  "created_at": "2013-05-23T10:25:34Z",
  "updated_at": "2017-02-28T12:07:34Z"
}